easierquant/__init__.py
easierquant/base.py
easierquant-0.0.2.dist-info/LICENSE
easierquant-0.0.2.dist-info/METADATA
easierquant-0.0.2.dist-info/WHEEL
easierquant-0.0.2.dist-info/top_level.txt
easierquant-0.0.2.dist-info/RECORD
