Metadata-Version: 2.1
Name: easierquant
Version: 0.0.2
Summary: a quant tool
Home-page: https://gitee.com/aierwiki/easierquant
Author: Tang Yubin
Author-email: tang-yu-bin@qq.com
License: UNKNOWN
Platform: UNKNOWN
Classifier: Programming Language :: Python :: 3
Classifier: License :: OSI Approved :: MIT License
Classifier: Operating System :: OS Independent
License-File: LICENSE
